backboard/__init__.py
backboard/_version.py
backboard/client.py
backboard/exceptions.py
backboard/models.py
backboard_sdk-1.4.10.dist-info/licenses/LICENSE
backboard_sdk-1.4.10.dist-info/METADATA
backboard_sdk-1.4.10.dist-info/WHEEL
backboard_sdk-1.4.10.dist-info/top_level.txt
backboard_sdk-1.4.10.dist-info/RECORD
